wintermute/__init__.py
wintermute-0.0.1.dist-info/LICENSE
wintermute-0.0.1.dist-info/METADATA
wintermute-0.0.1.dist-info/WHEEL
wintermute-0.0.1.dist-info/top_level.txt
wintermute-0.0.1.dist-info/RECORD
